lab4/sequence_detector.v
module sequence_detector(input clk, input in, output out);
  parameter S0 = 2'b00, S1 = 2'b01, S2 = 2'b10, S3 = 2'b11;

  reg out;
  reg [1:0] curr_state = S0, next_state = S0;

  always @(posedge clk) begin
    curr_state <= next_state;
  end

  always @(curr_state or in) begin
    case(curr_state)
      S0 : begin
        if(in) next_state = S1;
        else next_state = S0;

        out = 1'b0;
      end

      S1 : begin
        if(!in) next_state = S2;
        else next_state = S1;

        out = 1'b0;
      end

      S2 : begin
        if(in) next_state = S3;
        else next_state = S0;

        out = 1'b0;
      end

      S3 : begin
        if(!in) begin
          next_state = S2;
          out = 1'b1;
        end
        else begin
          next_state = S1;
          out = 1'b0;
        end
      end
    endcase
  end

endmodule

lab4/sequence_detector_tb.v
`timescale 1ps/1ps
`include "sequence_detector.v"

module sequence_detector_tb();

  reg clk, in;
  wire out;
  wire [2:0] curr_state, next_state;

  always #10 clk = ~clk;

  sequence_detector uu0(.clk(clk), .in(in), .out(out));

  initial begin

    $dumpfile("sequence_detector_tb.vcd");
    $dumpvars(0, sequence_detector_tb);

    clk <= 0;
    in <= 0;
  
    // @(posedge clk) in <= 1;
    // @(posedge clk) in <= 1;
    // @(posedge clk) in <= 0;
    // @(posedge clk) in <= 1;
    // @(posedge clk) in <= 0;
    // @(posedge clk) in <= 1;
    // @(posedge clk) in <= 0;
    @(posedge clk) in <= 0;
    @(posedge clk) in <= 1;
    @(posedge clk) in <= 1;
    @(posedge clk) in <= 0;
    @(posedge clk) in <= 1;
    @(posedge clk) in <= 0;
    @(posedge clk) in <= 1;
    @(posedge clk) in <= 0;

    #100 $finish;
  end

endmodule

lab4/sequence_detector_tb.vcd
$date
	Mon Feb  6 12:45:38 2023
$end
$version
	Icarus Verilog
$end
$timescale
	1ps
$end
$scope module sequence_detector_tb $end
$var wire 1 ! out $end
$var reg 1 " clk $end
$var reg 1 # in $end
$scope module uu0 $end
$var wire 1 " clk $end
$var wire 1 # in $end
$var reg 2 $ curr_state [1:0] $end
$var reg 2 % next_state [1:0] $end
$var reg 1 ! out $end
$upscope $end
$upscope $end
$enddefinitions $end
#0
$dumpvars
b0 %
b0 $
0#
0"
0!
$end
#10
1"
#20
0"
#30
b1 %
1#
1"
#40
0"
#50
b1 $
1"
#60
0"
#70
b10 %
0#
1"
#80
0"
#90
b11 %
b10 $
1#
1"
#100
0"
#110
1!
b10 %
0#
b11 $
1"
#120
0"
#130
0!
b11 %
b10 $
1#
1"
#140
0"
#150
1!
b10 %
0#
b11 $
1"
#160
0"
#170
0!
b0 %
b10 $
1"
#180
0"
#190
b0 $
1"
