lab4/detector.v
module detector(in, out, clk);
    input in, clk;
    output reg out;
    reg [1:0] stt;
    reg [1:0] ns;
    initial begin
        stt <= 2'b00;
    end
    always @(stt or in) begin : combi
        ns[0] <= in;
        ns[1] <= (stt[0] & ~stt[1] & ~in) | (~stt[0] & stt[1] & in) | (stt[0] & stt[1] & ~in);
    end
    always @(posedge clk)begin : sequence
        stt <= ns;
    end
    always @(clk) begin : opt
        out <= stt[0] & stt[1] & ~in;
    end
endmodule

lab4/at_det_tb.v
`timescale 1ns/1ps
`include "detector.v"
module tb;
    reg in;
    wire out;
    wire [1:0] st;
    reg clk;
    initial begin
        clk <= 0;
        forever begin
            #5 clk <= ~clk;
        end
    end 
    integer i;
    detector d0(in, out, clk);
    initial begin
        $dumpfile("waveform.vcd");
        $dumpvars;
        in <= 0; #10
        $display("in = %b, out = %b", in, out);
        in <= 0; #10
        $display("in = %b, out = %b", in, out);
        in <= 1; #10
        $display("in = %b, out = %b", in, out);
        in <= 0; #10
        $display("in = %b, out = %b", in, out);
        in <= 1; #10
        $display("in = %b, out = %b", in, out);
        in <= 0; #10
        $display("in = %b, out = %b", in, out);
        in <= 0; #10
        $display("in = %b, out = %b", in, out);
        in <= 1; #10
        $display("in = %b, out = %b", in, out);
        $finish;
    end
endmodule

lab4/waveform.vcd
$date
	Mon Feb  6 12:50:31 2023
$end
$version
	Icarus Verilog
$end
$timescale
	1ps
$end
$scope module tb $end
$var wire 1 ! out $end
$var reg 1 " clk $end
$var reg 1 # in $end
$scope module d0 $end
$var wire 1 " clk $end
$var wire 1 # in $end
$var reg 2 $ ns [1:0] $end
$var reg 1 ! out $end
$var reg 2 % stt [1:0] $end
$scope begin combi $end
$upscope $end
$scope begin opt $end
$upscope $end
$scope begin sequence $end
$upscope $end
$upscope $end
$upscope $end
$enddefinitions $end
#0
$dumpvars
b0 %
b0 $
0#
0"
0!
$end
#5000
1"
#10000
0"
#15000
1"
#20000
b1 $
0"
1#
#25000
b1 %
1"
#30000
b10 $
0"
0#
#35000
b0 $
b10 %
1"
#40000
b11 $
0"
1#
#45000
b1 $
b11 %
1"
#50000
1!
b10 $
0"
0#
#55000
b0 $
b10 %
1"
#60000
0!
0"
#65000
b0 %
1"
#70000
b1 $
0"
1#
#75000
b1 %
1"
